cookiesManager/__init__.py
cookiesManager/cookiesManager.py
extensionsManager/__init__.py
extensionsManager/extensionsManager.py
glogin-2025.5.1638.dist-info/licenses/LICENSE
gologin/__init__.py
gologin/gologin.py
gologin/cookiesManager/__init__.py
gologin/cookiesManager/cookiesManager.py
gologin/extensionsManager/__init__.py
gologin/extensionsManager/extensionsManager.py
glogin-2025.5.1638.dist-info/METADATA
glogin-2025.5.1638.dist-info/WHEEL
glogin-2025.5.1638.dist-info/top_level.txt
glogin-2025.5.1638.dist-info/RECORD
