Metadata-Version: 2.4
Name: glogin
Version: 2025.5.1638
Summary: python package
Author: tcp2
Requires-Python: >=3.5
License-File: LICENSE
Requires-Dist: requests
Requires-Dist: psutil
Dynamic: author
Dynamic: description-content-type
Dynamic: license-file
Dynamic: requires-dist
Dynamic: requires-python
Dynamic: summary
